podcast_analyzer/__init__.py
podcast_analyzer/admin.py
podcast_analyzer/apps.py
podcast_analyzer/exceptions.py
podcast_analyzer/forms.py
podcast_analyzer/models.py
podcast_analyzer/py.typed
podcast_analyzer/receivers.py
podcast_analyzer/tasks.py
podcast_analyzer/urls.py
podcast_analyzer/utils.py
podcast_analyzer/views.py
podcast_analyzer/locale/.keep
podcast_analyzer/management/__init__.py
podcast_analyzer/management/commands/__init__.py
podcast_analyzer/management/commands/seed_database_itunes.py
podcast_analyzer/migrations/0001_initial.py
podcast_analyzer/migrations/0002_alter_person_img_url_alter_person_url.py
podcast_analyzer/migrations/0003_alter_podcast_itunes_categories.py
podcast_analyzer/migrations/0004_remove_episode_tags_delete_tagulous_episode_tags.py
podcast_analyzer/migrations/0005_analysisgroup_description.py
podcast_analyzer/migrations/0006_person_merged_at_person_merged_into.py
podcast_analyzer/migrations/0007_person_avatar.py
podcast_analyzer/migrations/__init__.py
podcast_analyzer/static/.keep
podcast_analyzer/templates/base.html
podcast_analyzer/templates/podcast_analyzer/analysisgroup_confirm_delete.html
podcast_analyzer/templates/podcast_analyzer/analysisgroup_detail.html
podcast_analyzer/templates/podcast_analyzer/analysisgroup_form.html
podcast_analyzer/templates/podcast_analyzer/analysisgroup_list.html
podcast_analyzer/templates/podcast_analyzer/app_base.html
podcast_analyzer/templates/podcast_analyzer/app_entry.html
podcast_analyzer/templates/podcast_analyzer/episode_confirm_delete.html
podcast_analyzer/templates/podcast_analyzer/episode_detail.html
podcast_analyzer/templates/podcast_analyzer/episode_form.html
podcast_analyzer/templates/podcast_analyzer/episode_list.html
podcast_analyzer/templates/podcast_analyzer/person_confirm_delete.html
podcast_analyzer/templates/podcast_analyzer/person_confirm_merge.html
podcast_analyzer/templates/podcast_analyzer/person_detail.html
podcast_analyzer/templates/podcast_analyzer/person_form.html
django_podcast_analyzer-0.6.0.dist-info/METADATA
django_podcast_analyzer-0.6.0.dist-info/WHEEL
django_podcast_analyzer-0.6.0.dist-info/licenses/LICENSE
django_podcast_analyzer-0.6.0.dist-info/RECORD
