Metadata-Version: 2.4
Name: django-podcast-analyzer
Version: 0.6.0
Summary: A simple Django app that tracks podcast feeds and provides some useful metrics about them.
Project-URL: Repository, https://codeberg.org/andrlik/django-podcast-analyzer
Project-URL: Homepage, https://codeberg.org/andrlik/django-podcast-analyzer
Project-URL: Documentation, https://django-podcast-analyzer.readthedocs.io/en/latest/
Author-email: Daniel Andrlik <daniel@andrlik.org>
License-Expression: BSD-3-Clause
License-File: LICENSE
Classifier: Development Status :: 4 - Beta
Classifier: Framework :: Django
Classifier: Framework :: Django :: 5.2
Classifier: License :: OSI Approved :: BSD License
Classifier: Programming Language :: Python :: 3.12
Classifier: Programming Language :: Python :: 3.13
Classifier: Programming Language :: Python :: 3.14
Requires-Python: >=3.12
Requires-Dist: django-q2>=1.7.2
Requires-Dist: django-rich>=1.11.0
Requires-Dist: django-tagulous>=2.1.0
Requires-Dist: django-typer>=2.2.2
Requires-Dist: django>=5.2.0
Requires-Dist: httpx[brotli,http2]>=0.27.2
Requires-Dist: pillow>=10.4.0
Requires-Dist: podcastparser>=0.6.10
Requires-Dist: python-magic>=0.4.27
